tcetnlp/__init__.py
tcetnlp/tcetnlpfinal.py
tcetnlpfinal-0.1.0.dist-info/METADATA
tcetnlpfinal-0.1.0.dist-info/WHEEL
tcetnlpfinal-0.1.0.dist-info/top_level.txt
tcetnlpfinal-0.1.0.dist-info/RECORD
