Metadata-Version: 2.1
Name: tcetnlpfinal
Version: 0.1.0
Summary: A brief description of your project.
Author: Ishaan
Author-email: ishaang1410@gmail.com
Classifier: Programming Language :: Python :: 3
Classifier: License :: OSI Approved :: MIT License
Classifier: Operating System :: OS Independent
Requires-Python: >=3.6
